shiftedstorage/__init__.py
shiftedstorage/cli.py
shiftedstorage/compose.py
shiftedstorage/compose.yml
shiftedstorage-0.2.3.dist-info/WHEEL
shiftedstorage-0.2.3.dist-info/entry_points.txt
shiftedstorage-0.2.3.dist-info/METADATA
shiftedstorage-0.2.3.dist-info/RECORD
