Metadata-Version: 2.3
Name: shiftedstorage
Version: 0.2.3
Summary: Distributed storage for community archives using ipfs-cluster, Tailscale and Docker
Requires-Dist: click>=8.2.1
Requires-Dist: pyyaml>=6.0.2
Requires-Python: >=3.13
